text_classifier/__init__.py
text_classifier/__main__.py
text_classifier/classifier.py
text_classifier/cli.py
text_classifier/config_loader.py
text_classifier/console_output.py
text_classifier/io_excel.py
text_classifier/rules.py
excel_text_classifier-0.1.1.dist-info/METADATA
excel_text_classifier-0.1.1.dist-info/WHEEL
excel_text_classifier-0.1.1.dist-info/entry_points.txt
excel_text_classifier-0.1.1.dist-info/top_level.txt
excel_text_classifier-0.1.1.dist-info/RECORD
