Metadata-Version: 2.4
Name: excel-text-classifier
Version: 0.1.1
Summary: Excel multi-label text classifier with JSON/YAML/Excel rule configs and priority/exclusive rules.
Author-email: Chandler <275737875@qq.com>
License: MIT
Requires-Python: >=3.9
Requires-Dist: pandas>=1.5
Requires-Dist: typer>=0.9
Requires-Dist: openpyxl>=3.1
Requires-Dist: PyYAML>=6
Provides-Extra: rich
Requires-Dist: rich>=13; extra == "rich"
